simplefancontroller/__init__.py
simplefancontroller/log.py
simplefancontroller/main.py
simplefancontroller/settings.py
simplefancontroller/api/__init__.py
simplefancontroller/api/app.py
simplefancontroller/api/jwt_bearer.py
simplefancontroller/api/schemas.py
simplefancontroller/api/user_manager.py
simplefancontroller/api/routers/__init__.py
simplefancontroller/api/routers/auth.py
simplefancontroller/api/routers/controller.py
simplefancontroller/api/routers/fans.py
simplefancontroller/api/routers/settings.py
simplefancontroller/sfc/__init__.py
simplefancontroller/sfc/controller.py
simplefancontroller/sfc/data_manager.py
simplefancontroller/sfc/database.py
simplefancontroller/sfc/fans.py
simplefancontroller/sfc/settings.py
simplefancontroller/sfc/storage.py
simplefancontroller/sfc/thread_manager.py
simplefancontroller/ui/__init__.py
simplefancontroller/ui/app.py
simplefancontroller/ui/html_utils.py
simplefancontroller/ui/settings.py
simplefancontroller/ui/routes/__init__.py
simplefancontroller-0.0.1.dist-info/LICENSE
simplefancontroller-0.0.1.dist-info/METADATA
simplefancontroller-0.0.1.dist-info/WHEEL
simplefancontroller-0.0.1.dist-info/top_level.txt
simplefancontroller-0.0.1.dist-info/RECORD
