Metadata-Version: 2.1
Name: simplefancontroller
Version: 0.0.1
Summary: Simple controller for 2- and 4- pin fans via GPIO
Home-page: https://gitlab.com/tiuri/simplefancontroller
Author: Georg Arbesser-Rastburg
Author-email: arbesser.georg@gmail.com
License: MIT
Project-URL: Documentation, https://simplefancontroller.readthedocs.io
Platform: UNKNOWN
Classifier: Development Status :: 4 - Beta
Classifier: Intended Audience :: Developers
Classifier: License :: OSI Approved :: MIT License
Classifier: Programming Language :: Python :: 3.9
Classifier: Programming Language :: Python :: 3.10
Classifier: Typing :: Typed
License-File: LICENSE
Requires-Dist: gpiozero
Requires-Dist: influxdb-client
Requires-Dist: numpy
Requires-Dist: passlib
Requires-Dist: pydantic[email]
Requires-Dist: fastapi
Requires-Dist: jinja2
Requires-Dist: uvicorn
Requires-Dist: PyJWT
Requires-Dist: python-decouple
Requires-Dist: requests
